{
  "db": "PostgreSQL",
  "0db26b8435c1a9b13cbf45e5e257242bd42da5f515999789a04a6c3726534c9f": {
    "query": "INSERT INTO definitions(version, definition, schema) VALUES('1.0.0', $1, $2)",
    "describe": {
      "columns": [],
      "parameters": {
        "Left": [
          "Json",
          "Uuid"
        ]
      },
      "nullable": []
    }
  },
  "2897e1eccb96ae8cca7a77ef6aab4c43eeb10bc0f7cb9a8cddcd71b33fe387aa": {
    "query": "INSERT INTO schemas(id, name, type, queue, query_addr) VALUES($1, $2, $3, $4, $5)",
    "describe": {
      "columns": [],
      "parameters": {
        "Left": [
          "Uuid",
          "Varchar",
          {
            "Custom": {
              "name": "schema_type",
              "kind": {
                "Enum": [
                  "document_storage",
                  "timeseries"
                ]
              }
            }
          },
          "Varchar",
          "Varchar"
        ]
      },
      "nullable": []
    }
  },
  "28b12f7ab673125a1a3b2248a4c18e7425b669469a3f59992c8e1a582f7ebae4": {
    "query": "SELECT id FROM schemas WHERE id = $1",
    "describe": {
      "columns": [
        {
          "ordinal": 0,
          "name": "id",
          "type_info": "Uuid"
        }
      ],
      "parameters": {
        "Left": [
          "Uuid"
        ]
      },
      "nullable": [
        false
      ]
    }
  },
  "3ac9272ad393449397f0b44aaf25c93cba5cda05ce20c8236d5419b239237190": {
    "query": "SELECT id, name, queue, query_addr, type as \"type: _\" FROM schemas",
    "describe": {
      "columns": [
        {
          "ordinal": 0,
          "name": "id",
          "type_info": "Uuid"
        },
        {
          "ordinal": 1,
          "name": "name",
          "type_info": "Varchar"
        },
        {
          "ordinal": 2,
          "name": "queue",
          "type_info": "Varchar"
        },
        {
          "ordinal": 3,
          "name": "query_addr",
          "type_info": "Varchar"
        },
        {
          "ordinal": 4,
          "name": "type: _",
          "type_info": {
            "Custom": {
              "name": "schema_type",
              "kind": {
                "Enum": [
                  "document_storage",
                  "timeseries"
                ]
              }
            }
          }
        }
      ],
      "parameters": {
        "Left": []
      },
      "nullable": [
        false,
        false,
        false,
        false,
        false
      ]
    }
  },
  "49d2d42127582ab4aa35990f60d0bcee19517f24a2ad76051729db8452a7d583": {
    "query": "UPDATE schemas SET name = $1, type = $2, queue = $3, query_addr = $4 WHERE id = $5",
    "describe": {
      "columns": [],
      "parameters": {
        "Left": [
          "Varchar",
          {
            "Custom": {
              "name": "schema_type",
              "kind": {
                "Enum": [
                  "document_storage",
                  "timeseries"
                ]
              }
            }
          },
          "Varchar",
          "Varchar",
          "Uuid"
        ]
      },
      "nullable": []
    }
  },
  "56b562f4c3bc721a42ee915e7fcfd26d5b83c6e7609003e0b694c0b9bd975215": {
    "query": "SELECT id, name, queue, query_addr, type as \"type: _\" FROM schemas WHERE id = $1",
    "describe": {
      "columns": [
        {
          "ordinal": 0,
          "name": "id",
          "type_info": "Uuid"
        },
        {
          "ordinal": 1,
          "name": "name",
          "type_info": "Varchar"
        },
        {
          "ordinal": 2,
          "name": "queue",
          "type_info": "Varchar"
        },
        {
          "ordinal": 3,
          "name": "query_addr",
          "type_info": "Varchar"
        },
        {
          "ordinal": 4,
          "name": "type: _",
          "type_info": {
            "Custom": {
              "name": "schema_type",
              "kind": {
                "Enum": [
                  "document_storage",
                  "timeseries"
                ]
              }
            }
          }
        }
      ],
      "parameters": {
        "Left": [
          "Uuid"
        ]
      },
      "nullable": [
        false,
        false,
        false,
        false,
        false
      ]
    }
  },
  "805432b49a86978f2f667b331dd2aa6330fdc08f7f5f29a51d0a899035f73201": {
    "query": "SELECT version, definition FROM definitions WHERE schema = $1",
    "describe": {
      "columns": [
        {
          "ordinal": 0,
          "name": "version",
          "type_info": "Varchar"
        },
        {
          "ordinal": 1,
          "name": "definition",
          "type_info": "Json"
        }
      ],
      "parameters": {
        "Left": [
          "Uuid"
        ]
      },
      "nullable": [
        false,
        false
      ]
    }
  },
  "ae1ae494dfd5fded571f046d9dcda3692d58e30536ba13c312c6a69093d9d27e": {
    "query": "SELECT definition FROM definitions WHERE schema = $1 and version = $2",
    "describe": {
      "columns": [
        {
          "ordinal": 0,
          "name": "definition",
          "type_info": "Json"
        }
      ],
      "parameters": {
        "Left": [
          "Uuid",
          "Text"
        ]
      },
      "nullable": [
        false
      ]
    }
  },
  "b25ace5778cf2f001f694da34beae588824aa5a8b474d7e2a66f0ae72ccc0f27": {
    "query": "SELECT version FROM definitions WHERE schema = $1",
    "describe": {
      "columns": [
        {
          "ordinal": 0,
          "name": "version",
          "type_info": "Varchar"
        }
      ],
      "parameters": {
        "Left": [
          "Uuid"
        ]
      },
      "nullable": [
        false
      ]
    }
  },
  "b95439e39cea0f259edafc05542d656d5426f472b1c7c7e434aa15b4523abe5d": {
    "query": "SELECT id, name, queue, query_addr, type as \"type: _\" FROM schemas ORDER BY name",
    "describe": {
      "columns": [
        {
          "ordinal": 0,
          "name": "id",
          "type_info": "Uuid"
        },
        {
          "ordinal": 1,
          "name": "name",
          "type_info": "Varchar"
        },
        {
          "ordinal": 2,
          "name": "queue",
          "type_info": "Varchar"
        },
        {
          "ordinal": 3,
          "name": "query_addr",
          "type_info": "Varchar"
        },
        {
          "ordinal": 4,
          "name": "type: _",
          "type_info": {
            "Custom": {
              "name": "schema_type",
              "kind": {
                "Enum": [
                  "document_storage",
                  "timeseries"
                ]
              }
            }
          }
        }
      ],
      "parameters": {
        "Left": []
      },
      "nullable": [
        false,
        false,
        false,
        false,
        false
      ]
    }
  },
  "c96cb1f32965b7da8c440abde118725e31f6502dca9d2352093e094abca6d1a3": {
    "query": "SELECT version, definition, schema FROM definitions",
    "describe": {
      "columns": [
        {
          "ordinal": 0,
          "name": "version",
          "type_info": "Varchar"
        },
        {
          "ordinal": 1,
          "name": "definition",
          "type_info": "Json"
        },
        {
          "ordinal": 2,
          "name": "schema",
          "type_info": "Uuid"
        }
      ],
      "parameters": {
        "Left": []
      },
      "nullable": [
        false,
        false,
        false
      ]
    }
  },
  "e9f34565e0de9b0d05ed897535bf6c53539aaef32a93f9a2e22c5a65ee5501d1": {
    "query": "INSERT INTO definitions(version, definition, schema) VALUES($1, $2, $3)",
    "describe": {
      "columns": [],
      "parameters": {
        "Left": [
          "Varchar",
          "Json",
          "Uuid"
        ]
      },
      "nullable": []
    }
  }
}